pyuppaal/__init__.py
pyuppaal/build_cg.py
pyuppaal/monitors.py
pyuppaal/nta.py
pyuppaal/pyuppaal.py
pyuppaal/tracer.py
pyuppaal/umodel.py
pyuppaal/verifyta.py
pyuppaal/utap/__init__.py
pyuppaal/utap/tracer.exe
pyuppaal/utap/tracer_darwin
pyuppaal/utap/tracer_linux
pyuppaal-1.2.0.dist-info/LICENSE
pyuppaal-1.2.0.dist-info/METADATA
pyuppaal-1.2.0.dist-info/WHEEL
pyuppaal-1.2.0.dist-info/top_level.txt
pyuppaal-1.2.0.dist-info/RECORD
