Metadata-Version: 2.1
Name: pyuppaal
Version: 1.2.0
Summary: A research tool that can simulate, verify or modify UPPAAL models with python. It can also help to analyze counter-examples in .xml format
Home-page: https://github.com/Jack0Chan/pyuppaal
Author: Jack0Chan
Author-email: 
Project-URL: Bug Tracker, https://github.com/Jack0Chan/pyuppaal/issues
Classifier: Programming Language :: Python :: 3
Classifier: License :: OSI Approved :: MIT License
Classifier: Operating System :: OS Independent
Requires-Python: >=3.6
License-File: LICENSE
